random_password_generator/__init__.py
random_password_generator/__main__.py
tests/__init__.py
tests/conftest.py
tests/test_random_password_generator.py
busie_random_password_generator-0.0.1.dist-info/LICENSE
busie_random_password_generator-0.0.1.dist-info/METADATA
busie_random_password_generator-0.0.1.dist-info/WHEEL
busie_random_password_generator-0.0.1.dist-info/top_level.txt
busie_random_password_generator-0.0.1.dist-info/RECORD
