Metadata-Version: 2.1
Name: busie-random-password-generator
Version: 0.0.1
Summary: A cryptographically random and secure random password generator
Home-page: https://github.com/BPerry24/random-password-generator.git
Author: Brady Perry
Author-email: brdyprry@gmail.com
License: UNKNOWN
Platform: UNKNOWN
Classifier: Programming Language :: Python :: 3
Classifier: License :: OSI Approved :: MIT License
Classifier: Operating System :: OS Independent
Requires-Python: >=3.6
